mapvbvd/__init__.py
mapvbvd/_attrdict.py
mapvbvd/_version.py
mapvbvd/mapVBVD.py
mapvbvd/read_twix_hdr.py
mapvbvd/twix_map_obj.py
pyMapVBVD-0.6.1.dist-info/LICENSE
pyMapVBVD-0.6.1.dist-info/METADATA
pyMapVBVD-0.6.1.dist-info/WHEEL
pyMapVBVD-0.6.1.dist-info/top_level.txt
pyMapVBVD-0.6.1.dist-info/RECORD
