Metadata-Version: 2.1
Name: pyMapVBVD
Version: 0.6.1
Summary: Python twix file reader
Home-page: https://github.com/wtclarke/pymapvbvd
Author: Will Clarke
Author-email: william.clarke@ndcn.ox.ac.uk
Classifier: Programming Language :: Python :: 3
Classifier: Programming Language :: Python :: 3.9
Classifier: Programming Language :: Python :: 3.10
Classifier: Programming Language :: Python :: 3.11
Classifier: Programming Language :: Python :: 3.12
Classifier: License :: OSI Approved :: MIT License
Classifier: Operating System :: OS Independent
Requires-Python: >=3.9
License-File: LICENSE
Requires-Dist: numpy>=1.26
Requires-Dist: tqdm
Requires-Dist: scipy>=1.13
Requires-Dist: matplotlib
Requires-Dist: h5py
Requires-Dist: six
Provides-Extra: tests
Requires-Dist: pytest; extra == "tests"
